babyagi/__init__.py
babyagi/api/__init__.py
babyagi/dashboard/__init__.py
babyagi/dashboard/static/css/style.css
babyagi/dashboard/static/js/dashboard.js
babyagi/dashboard/static/js/function_details.js
babyagi/dashboard/static/js/function_graph.js
babyagi/dashboard/static/js/log_dashboard.js
babyagi/dashboard/static/js/log_graph.js
babyagi/dashboard/templates/base.html
babyagi/dashboard/templates/chat.html
babyagi/dashboard/templates/function_details.html
babyagi/dashboard/templates/function_graph.html
babyagi/dashboard/templates/function_graph_3d.html
babyagi/dashboard/templates/function_graph_mermaid.html
babyagi/dashboard/templates/index.html
babyagi/dashboard/templates/log_page.html
babyagi/dashboard/templates/log_relationship_graph.html
babyagi/dashboard/templates/logs_dashboard.html
babyagi/functionz/__init__.py
babyagi/functionz/core/__init__.py
babyagi/functionz/core/execution.py
babyagi/functionz/core/framework.py
babyagi/functionz/core/registration.py
babyagi/functionz/db/__init__.py
babyagi/functionz/db/base_db.py
babyagi/functionz/db/db_router.py
babyagi/functionz/db/local_db.py
babyagi/functionz/db/models.py
babyagi/functionz/packs/default/ai_functions.py
babyagi/functionz/packs/default/default_functions.py
babyagi/functionz/packs/default/function_calling_chat.py
babyagi/functionz/packs/default/os.py
babyagi/functionz/packs/drafts/choose_or_create_function.py
babyagi/functionz/packs/drafts/code_writing_functions.py
babyagi/functionz/packs/drafts/generate_function.py
babyagi/functionz/packs/drafts/generate_own_function.py
babyagi/functionz/packs/drafts/react_agent.py
babyagi/functionz/packs/drafts/self_build.py
babyagi/functionz/packs/drafts/self_build2.py
babyagi/functionz/packs/drafts/user_db.py
babyagi/functionz/packs/plugins/airtable.py
babyagi/functionz/packs/plugins/augie.py
babyagi/functionz/packs/plugins/e2b.py
babyagi/functionz/packs/plugins/firecrawl.py
babyagi/functionz/packs/plugins/harmonic.py
babyagi/functionz/packs/plugins/payman.py
babyagi-0.1.4.dist-info/METADATA
babyagi-0.1.4.dist-info/WHEEL
babyagi-0.1.4.dist-info/entry_points.txt
babyagi-0.1.4.dist-info/top_level.txt
babyagi-0.1.4.dist-info/RECORD
