Metadata-Version: 2.1
Name: babyagi
Version: 0.1.4
Summary: An experimental prototype framework for building self building autonomous agents.
Home-page: https://github.com/yoheinakajima/babyagi
Author: Yohei Nakajima
Author-email: babyagi@untapped.vc
Project-URL: Author, https://x.com/yoheinakajima
Keywords: AGI,AI,Framework,Baby AGI
Classifier: Programming Language :: Python :: 3
Classifier: License :: OSI Approved :: MIT License
Classifier: Operating System :: OS Independent
Requires-Python: >=3.6
Requires-Dist: Flask>=2.0.0
Requires-Dist: sqlalchemy<2.0,>=1.4
Requires-Dist: cryptography
Requires-Dist: scikit-learn
Requires-Dist: litellm
Requires-Dist: openai
